admmcoml/__init__.py
admmcoml/_train_framework.so
admmcoml/train_framework.py
admmcoml/try.py
admmcoml-0.1.0.dist-info/METADATA
admmcoml-0.1.0.dist-info/WHEEL
admmcoml-0.1.0.dist-info/top_level.txt
admmcoml-0.1.0.dist-info/RECORD
